{"category":"問卦","title":"[問卦] 有沒有慈濟是台灣的一個奇蹟的八卦","author":"phoxonic0510","content":"\n事情是這樣的，\n\n魯肥宅我今天被家人拉著去參加慈濟歲末祝福，\n\n裡面看到介紹慈濟到各國援助創立分院，\n\n感覺好像很厲害，\n\n不過想想似乎除了紅十字以外，\n\n似乎沒有類似的跨國援助機構了，\n\n更別說是出於小小的臺灣，\n\n有沒有慈濟是台灣的一個奇蹟的八卦\n\n--\nSent from my Android\n\n--\n","pushes":[{"user":"Nappa","replies":[{"type":"→","content":"我猜應該蠻多的"}]},{"user":"haoto","replies":[{"type":"→","content":"全台最大地主 拿來蓋社會住宅不就功德無量 ㄏㄏ"},{"type":"→","content":"作夢吧 除了諾貝爾獎的委員以外有人聽過喔XDDDDDDDD"}]},{"user":"YishengSu","replies":[{"type":"→","content":"偽善的集合體"}]},{"user":"white0115","replies":[{"type":"推","content":"不喜歡 但不可否認在外國人眼裡 知名度可能甚過於台灣"}]},{"user":"gdgy","replies":[{"type":"→","content":"卡人是魏家的好朋友"}]},{"user":"kiwi816422","replies":[{"type":"推","content":"國外知名度比台灣大+2"}]},{"user":"s1s2s3s4","replies":[{"type":"→","content":"晚上也被家人拉去參加"}]},{"user":"ItsTimeToGo","replies":[{"type":"推","content":"再給他一百年看會發展成怎樣"}]},{"user":"flyhattmann","replies":[{"type":"→","content":"房子越來越多"}]},{"user":"G8MO","replies":[{"type":"→","content":"我覺得沒必要在那邊酸拉! 社會上有這樣的團體應該感謝"}]}]}