{"category":"問卦","title":"[問卦] 有沒有重低音 不算噪音汙染的八卦","author":"HD0621","content":"\n如果隔壁鄰居 家裡很有錢\n\n裝 那種 9.1ch  家庭劇院\n\n如果家都會聽到一堆 重低音 蹦 蹦 蹦 的聲音\n\n聽久還蠻煩的\n\n可是 重低音 又非常難測量 分貝數 和 頻率又很難測出 超標\n\n不像那種歌放超大聲 分貝數很簡單就能檢測超標\n\n有沒有重低音 算不算噪音的八卦?\n\n聽說 重低音 非常難界定是否為噪音?\n\n難道真的要等發瘋去看精神科 才能 提民事嗎?\n\n有八卦嗎?\n\n\n--\n","pushes":[{"user":"kana0228","replies":[{"type":"→","content":"卡卡的董資董茲"}]},{"user":"milkyway168","replies":[{"type":"→","content":"01有一篇用共振音箱反擊的文章   你可以參考"},{"type":"→","content":"標題~~樓上吵屢勸不聽 有個東西真的好用"}]},{"user":"asiakid","replies":[{"type":"→","content":"               噗滋噗滋"}]},{"user":"sd09090","replies":[{"type":"→","content":"我家隔壁現在就在冬冬冬...它每個星期天都會開音響自嗨"}]},{"user":"www5566","replies":[{"type":"→","content":"共振喇叭記得買瓦數大一點 給他一槍斃命"}]},{"user":"wl00725348","replies":[{"type":"推","content":"我記得之前不是有人拿無線電發射訊號的東西(忘了叫什"},{"type":"→","content":"麼)對著人家裡射嗎，然後沒多久就搬家了"}]}]}