{"category":"問卦","title":"[問卦] 下一個九把刀是誰","author":"lifepass","content":"\n九把刀可稱為近幾年文壇奇蹟\n\n小說大賣、電影大賣\n\n無人能出其右\n\n他自封文壇周杰倫絕非浪得虛名\n\n大家覺得他還可以紅多久呢\n\n下一個崛起的明星又是誰呢？\n\n是即將拍電影的藤井樹\n\n還是輕小說天后御我呢\n\n--\n","pushes":[{"user":"mimi1020b","replies":[{"type":"→","content":"羅志祥 亞洲跳舞最棒 海珊最不愛打仗"}]},{"user":"krishuang","replies":[{"type":"推","content":"九層塔"}]},{"user":"CHANYII","replies":[{"type":"→","content":"他早就不紅了…"}]},{"user":"softseaweed","replies":[{"type":"→","content":"九把刀可以叫文學 也真神奇"}]},{"user":"RNADNA","replies":[{"type":"推","content":"金庸吧"}]},{"user":"seuil","replies":[{"type":"→","content":"丸吧刃"}]},{"user":"ggly","replies":[{"type":"推","content":"朱學恆"}]},{"user":"theskyofblue","replies":[{"type":"→","content":"知名度是護玄  風格上是星子吧"}]},{"user":"milkyway168","replies":[{"type":"推","content":"去 SEX版找  那邊很多小說家"}]},{"user":"sumade5566","replies":[{"type":"→","content":"當然是某個愛幻想的小說家板主"}]},{"user":"sion1993","replies":[{"type":"噓","content":"你把女王放在哪裡?"}]},{"user":"hhd22","replies":[{"type":"推","content":"以後沒小說家了啦，應該會出現某種劇情製造程式，人物設定"},{"type":"→","content":"好自己跑故事"},{"type":"推","content":"還有現在的電玩遊戲就是未來小說型式"}]},{"user":"seacore07","replies":[{"type":"推","content":"藤井樹是刀大前輩，但他早就被刀大幹掉了"}]},{"user":"rodey","replies":[{"type":"噓","content":"文壇奇跡咧   無人能出其右咧  你的滿足點還真高咧"}]},{"user":"lifepass","replies":[{"type":"→","content":"看好藤井樹拍電影後能崛起"}]}]}