{"category":"Re:","title":"Re: [問卦] live實力堅強的歌手？","author":"hayate232","content":"\n\n我覺得不一定要跟CD一樣\n\n如果有聽樂團的，會覺得 樂團Live各種驚奇!\n\n\n吉他彈錯，不要緊~技術好的都可以假裝SOLO或是變奏\n\n\nX 算是\"Live\" 很OK的\n\n\"X\" 這首 聽CD反而沒有看現場那麼熱血\n\n\n\n\n--\n      \n\n◤\n◣  ◢\n\n\n\n--\n南港展覽館那次 感覺整棟樓都快被跳壞了 囧\n板橋那時候我只是小屁孩..管太嚴拉\n","pushes":[{"user":"Beef","replies":[{"type":"→","content":"X的所有歌聽CD都沒有現場熱血好嗎........."},{"type":"推","content":"板體+1 Yoshiki在空中雙踏那次才叫熱血"}]},{"user":"Lillard5566","replies":[{"type":"→","content":"試舉出聽CD反而比現場熱血的歌曲:"}]},{"user":"makimakimaki","replies":[{"type":"→","content":"初音"}]},{"user":"hidexjapan","replies":[{"type":"→","content":"板體那場才經典阿,不枉費5000可惜之後都小場地了"}]},{"user":"cemin","replies":[{"type":"推","content":"一個樂團如果CD比現場熱血  這個團還有臉開LIVE也很有勇氣"}]},{"user":"Hotaruinori","replies":[{"type":"→","content":"水樹"}]},{"user":"zxvf","replies":[{"type":"推","content":"we are X!!!"}]},{"user":"hydeliu","replies":[{"type":"推","content":"板體超棒~ x很熱血"}]}]}