{"category":"新聞","title":"[新聞] LINE新功能「已讀要回：對方打字中」　網","author":"kosuke","content":"","pushes":[{"user":"iPhone4sW","replies":[{"type":"→","content":"瞎"}]},{"user":"orfan","replies":[{"type":"噓","content":"已讀 準備噓文中"}]},{"user":"solidmiss","replies":[{"type":"推","content":"幹  不能裝死了"}]},{"user":"linchw","replies":[{"type":"噓","content":"5F已尻"}]},{"user":"utley","replies":[{"type":"噓","content":"超爛的。有時候打一打再刪掉對方也知道"}]},{"user":"bruce511239","replies":[{"type":"噓","content":"已讀 去洗澡 :)"},{"type":"→","content":"根本沒必要這麼絕 不回的不管你怎麼設計就是不回"}]},{"user":"HiranoMiu","replies":[{"type":"噓","content":"反對"}]},{"user":"HD0621","replies":[{"type":"噓","content":"超爛 如果一直顯示...對方都沒回 。等到死阿"}]},{"user":"BlueBird5566","replies":[{"type":"噓","content":"樓下肥宅不會為了已讀不回不高興 因為名單沒有人"},{"type":"→","content":"看推文就知道一堆菜逼巴 2000年msn跟yahoo即時通就"},{"type":"→","content":"有了"}]},{"user":"happyary","replies":[{"type":"噓","content":"是想逼死誰…"}]},{"user":"Carmelo","replies":[{"type":"噓","content":"爛功能 給條生路吧"}]},{"user":"theskyofblue","replies":[{"type":"推","content":"根本沒差  現在一堆根本都不打開來看的好嗎"},{"type":"→","content":"跳出來知道內容  要回才開"}]},{"user":"rayxg","replies":[{"type":"推","content":"已讀不會是內建功能吧，很正常不是？"}]},{"user":"komifree","replies":[{"type":"噓","content":"幹"}]},{"user":"Xenogamer","replies":[{"type":"噓","content":"先洗澡掰"}]},{"user":"wonder007","replies":[{"type":"→","content":"....阿這不就iMessage? LINE是要完整模仿Apple嗎?"}]},{"user":"badblue","replies":[{"type":"噓","content":"人性與科技的拔河"}]},{"user":"YSJ543","replies":[{"type":"→","content":"肥宅以後傳訊正妹 對方連打字回都不肯XDDDDDDDDDDDDDDD"}]},{"user":"fuccwoman","replies":[{"type":"→","content":"這不是跟skype一樣嗎"}]},{"user":"a0913","replies":[{"type":"噓","content":"XDDD   愛抄"}]},{"user":"maxlin9527","replies":[{"type":"推","content":"嗯嗯 ㄏㄏ 去洗澡 又要重出江湖惹"}]},{"user":"Tass","replies":[{"type":"推","content":"咦？我怎麼記得當初有輸入中功能 後來改掉了 現在是改回來"},{"type":"→","content":"喔？"}]},{"user":"s850284","replies":[{"type":"推","content":"其實whatsapp2010年（或更早）早就有已讀跟typing的功能"},{"type":"→","content":"下次應該就是再學「最後上線時間」了吧"}]},{"user":"ASlover95","replies":[{"type":"推","content":"msn大概2006 07年就有了吧"}]},{"user":"ciplu","replies":[{"type":"推","content":"這很多傳訊軟體早就有了吧 hangout   fb 都有。早就習慣啦"}]},{"user":"cloudin","replies":[{"type":"噓","content":"靠杯不要"}]},{"user":"dragon159","replies":[{"type":"噓","content":"不要有任何訊息有很難嗎"},{"type":"→","content":"一堆討厭關不掉的功能 不想裝還不行 朋友好好"},{"type":"→","content":"朋友還好 公司要你裝你能不裝嗎 下班動不動就line你"},{"type":"→","content":"真的很重要不會打電話阿 Line什麼 沒看到好像我的錯"},{"type":"→","content":"看了不回也我的錯 我下班了不管上班的事情不行嗎"}]},{"user":"erik777","replies":[{"type":"推","content":"我想關掉已讀提示 = ="}]},{"user":"kahabu","replies":[{"type":"噓","content":"這功能QQ早就有了，要不要再順便抄一下QQ的優點"}]},{"user":"SuperUp","replies":[{"type":"→","content":"已讀不回很嚴重嗎？你真有重要事打電話ㄚ"}]},{"user":"zonegs","replies":[{"type":"噓","content":"快點實裝阿 期待看別人崩潰阿"}]},{"user":"willy10207","replies":[{"type":"噓","content":"抄 MSN 還不如把已讀功能拿掉"}]},{"user":"widec","replies":[{"type":"噓","content":"幹恁娘"}]},{"user":"Quickspace","replies":[{"type":"噓","content":"幹"}]},{"user":"Accolada","replies":[{"type":"噓","content":"可不可以還我MSN阿 J三小 用個圖也要花錢"}]},{"user":"colorfuldays","replies":[{"type":"噓","content":"拜託啟用\"使用者自動關閉已讀功能\" 討厭死了"}]},{"user":"t1520061217","replies":[{"type":"噓","content":"沒差啊 反正沒人跟我聊"}]},{"user":"cbate","replies":[{"type":"噓","content":"韓國APP"}]},{"user":"MW1220","replies":[{"type":"噓","content":"MSN早就有了…"}]},{"user":"ontherun3325","replies":[{"type":"噓","content":"那個圖片的女的是puma ccr嗎?"}]},{"user":"Charleston","replies":[{"type":"噓","content":"科技不是始終來自於人性嗎？這樣太不人性了吧！"}]},{"user":"goodsnk","replies":[{"type":"推","content":"白七"}]},{"user":"p3295153","replies":[{"type":"推","content":"怎不做一個功能 發送出訊息對方才會顯示已讀?  XD"}]},{"user":"YuenYang5566","replies":[{"type":"推","content":"之前即時通不就這樣嗎...[對方回覆訊息中...]"},{"type":"→","content":"是怎樣 = = 沒用過？"}]},{"user":"em77","replies":[{"type":"噓","content":":"}]},{"user":"spfd","replies":[{"type":"噓","content":"這不是MSN八百年前就有的功能嗎?  話說這壓力真的很大"}]}]}