{"category":"新聞","title":"[新聞] 竹科人也買不起房！最低月租5千蝸居7坪違","author":"humt59","content":"","pushes":[{"user":"amateuruser","replies":[{"type":"→","content":"工程師："}]},{"user":"ps20012001","replies":[{"type":"推","content":"今天看\"財經節目\" 拉一堆鳥人侃侃而談 這房千萬不能打"},{"type":"→","content":"左手 呼籲加強支援企業界 右手痛批 社會反商仇富"}]},{"user":"phaeton101","replies":[{"type":"推","content":"買到60坪幹嘛"}]},{"user":"clamperni","replies":[{"type":"推","content":"多騎個幾分鐘的車一坪就變十幾萬了"}]},{"user":"kevin31a2","replies":[{"type":"推","content":"關說一下就不用拆惹 意外嗎?"}]},{"user":"YahooTaiwan","replies":[{"type":"推","content":"宅宅就一個人住，住這麼大衝三小"}]},{"user":"Ives20130","replies":[{"type":"→","content":"你們的肝真沒競爭力"}]},{"user":"d9637568","replies":[{"type":"推","content":"金山街 恐怖"}]},{"user":"yukari8","replies":[{"type":"→","content":"擺宅物阿 我太魯佳里還沒地方擺耶"}]},{"user":"soulja28","replies":[{"type":"推","content":"舊的拍拍屁股走人 新的準備接爛攤子了"}]},{"user":"baggio1029","replies":[{"type":"推","content":"5千很便宜了好嗎 我租大安區的頂樓加蓋5坪9500"}]},{"user":"Hawking","replies":[{"type":"推","content":"賺的錢又大部分拿去付房租or房貸 房東建商爽爽收錢"}]},{"user":"z90546","replies":[{"type":"噓","content":"住金山街的  路過噓"}]},{"user":"InfinitiFX50","replies":[{"type":"推","content":"竹科新手村"}]},{"user":"bobobola","replies":[{"type":"推","content":"5000還有7坪 幹 叫他來大安區住"}]},{"user":"blacktea5566","replies":[{"type":"推","content":"這不是新聞阿 金山街根本呵呵"}]},{"user":"DivineAngel","replies":[{"type":"推","content":"5~6年也太久 身邊聽到幾乎都一兩年就有了"},{"type":"→","content":"而且台灣房價這麼不合理 又不是連家那種有錢法"},{"type":"→","content":"誰會無聊拿錢買CP質這麼低的房子"},{"type":"推","content":"空屋率這麼高還供不應求......?"},{"type":"→","content":"呵呵 政府真要打房就不會有這問題"}]},{"user":"turbomons","replies":[{"type":"推","content":"血汗賣肝還要被迫住高風險違建"}]},{"user":"haniah","replies":[{"type":"推","content":"拆違建當然較屋主出錢阿"}]},{"user":"kikicoco168","replies":[{"type":"推","content":"關新路一坪30w，是給家庭年收150~200以上買的，不然"},{"type":"推","content":"就要靠爸族了!! 旁邊很多舊房子便宜很多，還是買得起"},{"type":"→","content":"就怕你挑三撿四，看不上眼"}]},{"user":"sid3","replies":[{"type":"推","content":"房子供不應求當然漲  而且只會繼續漲不會跌"},{"type":"→","content":"房子是用錢堆出來的不是人  我有錢買個10間不行嗎?"},{"type":"→","content":"現在政府的偽打房政策只是打量不敢打價  畢竟高官手中一堆"}]},{"user":"jason1992999","replies":[{"type":"推","content":"5000一間7坪套房…台北表示："}]},{"user":"cacasi","replies":[{"type":"推","content":"爆肝幾年才有百萬，房子隨便就千萬起跳，當然買不起"}]},{"user":"ogisun","replies":[{"type":"推","content":"竹科新\"跪\" 另外 哪裡有七坪5000這麼便宜阿"}]},{"user":"haw561676","replies":[{"type":"→","content":"空屋又不租給別人啊"}]},{"user":"ffxx","replies":[{"type":"→","content":"鬼島房不是拿來給人住的 是拿來炒的"}]},{"user":"lancer0960","replies":[{"type":"→","content":"沒經費拆違建就先把它斷水電阿!"}]},{"user":"bruce511239","replies":[{"type":"→","content":"房子漲得比薪水兇阿 跟不上腳步"}]},{"user":"GaryMatthews","replies":[{"type":"推","content":"五隻羊：買不起就不要買阿 沒人逼你買"}]},{"user":"fish250504","replies":[{"type":"推","content":"難過"}]},{"user":"Hambowbow","replies":[{"type":"推","content":"五千七坪  超便宜"}]},{"user":"gekkojam","replies":[{"type":"推","content":"就這樣繼續搞下去啊 搞的沒有階級流動 只會向下沉淪"}]},{"user":"a0913","replies":[{"type":"推","content":"台北五千有五坪根本偷笑"}]},{"user":"season002","replies":[{"type":"推","content":"往好的方面看，在香港5000台幣就連棺材房都只能住半間"}]},{"user":"cloud520","replies":[{"type":"推","content":"跟台北比，好便宜，還有5成上漲空間"}]}]}