{"category":"Re:","title":"Re: [新聞] 竹市擺爛 8千違建得拆132年","author":"BleedWang","content":"\n新竹市\n\n由於園區一大堆不太講究生活品質的工程師在那邊的緣故\n\n既得利益者一直都是全台灣數一數二多的地方\n\n之前市長阿財剛上任 有想要掃蕩光復路的併排停車\n\n做了大概一個多月 光復路的確順很多\n\n但是沒多久那些光復路餿水業者就開始抗議\n\n阿財的民調也直直落 所以後來這個掃蕩舉動就不了了之\n\n抓違建這種事 牽扯到更多既得利益者\n\n我想應該是不太可能動\n\n--\n\n蚊子館是後來的事 那時候民調已經拉起來了 民調最慘是剛上任的時候\n\n","pushes":[{"user":"s860134","replies":[{"type":"推","content":"就跟停發年金一個道理嘛~"},{"type":"→","content":"更正  年金->慰問金"}]},{"user":"ru04hj4","replies":[{"type":"→","content":"民調直直落是因為掃蕩並排停車還是蓋了蚊子館"}]},{"user":"mayday24","replies":[{"type":"→","content":"不可質疑你的 幸福城市"}]},{"user":"wbreeze","replies":[{"type":"→","content":"是沒辦法講究生活品質 還是不想講究生活品質"}]},{"user":"kikicoco168","replies":[{"type":"→","content":"餿水業者!!!  有夠酸~XDD"}]},{"user":"cospergod","replies":[{"type":"推","content":"選女人都不講究了~怎麼可能講究房子"}]},{"user":"goodideals","replies":[{"type":"推","content":"我都懷疑慈雲橋官商勾結了勒 哪個智障歸畫的爛路線啊"}]}]}