{"category":"新聞","title":"[新聞] 驚喜！海軍少校服役半年返家　竟認不出枕","author":"palajuice","content":"","pushes":[{"user":"belmontc","replies":[{"type":"推","content":"因為只認得士官長了"}]},{"user":"royalsage","replies":[{"type":"→","content":"期待著~"}]},{"user":"vajra0001","replies":[{"type":"推","content":"變美女啦"}]},{"user":"madeinheaven","replies":[{"type":"→","content":"正常減重身上就不會有那種皮嗎?"}]},{"user":"cattgirl","replies":[{"type":"噓","content":"綠綠DER"}]},{"user":"erectus","replies":[{"type":"推","content":"多按摩會改善"},{"type":"推","content":"還有多吃膠原蛋白也會改善，肥胖紋就是局部缺乏膠原蛋白"}]},{"user":"kosuke","replies":[{"type":"推","content":"有順便發現兒子也越來越認不出來了嗎"}]},{"user":"freemail","replies":[{"type":"推","content":"好正 @@"}]},{"user":"HELLDIVER","replies":[{"type":"→","content":"有點像很難死光頭的女兒"}]},{"user":"blue999","replies":[{"type":"→","content":"下次再回來 會不會發現床上躺了別的人?"}]},{"user":"douge","replies":[{"type":"→","content":"沒有視訊嗎  還滿詭異的"}]},{"user":"MrSG","replies":[{"type":"推","content":"在軍艦上怎麼視訊"}]},{"user":"whitefox","replies":[{"type":"推","content":"身高170 cm以上的人,小腿都有那種皮"}]}]}