{"category":"Re:","title":"Re: [爆卦] 實拍中國的殺狗工廠(血腥慎入)","author":"arrenwu","content":"\n我看完這段影片了\n\n這影片裏面處理狗的方式是： 一棒敲暈 → 放血\n狗在被剝皮前應該是已經沒有知覺了\n\n這種作法不人道的地方是？\n\n--\n\n\n--\n但影片裏面都是一棒打暈啊\n負責把狗擊暈那個又不是說亂棒猛打，他的目的就只是擊暈而已\n用電流電暈跟一棒打暈的差別是？\n我是覺得那個狗場很髒啦\n","pushes":[{"user":"super1314159","replies":[{"type":"噓","content":"狗狗這麼可愛"}]},{"user":"sumade5566","replies":[{"type":"→","content":"殺雞都直接抓來就脖子放血了 怎沒人說殘忍?"},{"type":"→","content":"不過如果用電擊器把狗電暈後再宰，這觀感應該會好點"},{"type":"→","content":"傳統市場現在還是一堆直接割喉放血的 連電擊或打暈都"},{"type":"→","content":"沒有"}]},{"user":"chosenone","replies":[{"type":"→","content":"觀感不佳 而且用棒子容易力道和方位容易失準"}]},{"user":"waei","replies":[{"type":"推","content":"哈哈 說的對"}]},{"user":"www8787","replies":[{"type":"→","content":"環境不乾淨吧 不像超市看不到血湯 包裝漂亮所以噁心這樣"}]},{"user":"pedestrianA","replies":[{"type":"推","content":"雞鴨那些是先用電流暈眩吧...哪來直接放血"}]},{"user":"goodjeff","replies":[{"type":"推","content":"有差逆"}]},{"user":"ccc73123","replies":[{"type":"推","content":"我也覺得還好 我CARE的點是屠宰場太髒了"},{"type":"→","content":"難怪中國一堆奇怪的病傳出來"}]},{"user":"acgotaku","replies":[{"type":"→","content":"影片真的頗噁,講得這麼秋 我看真的到現場你會吐滿地"}]},{"user":"x335892","replies":[{"type":"噓","content":"愛吃狗的麻煩移民中國 噁心"}]},{"user":"ForeverDaivd","replies":[{"type":"→","content":"噓，強國人思維，你確定每隻都敲暈? 上隻有病染到下"},{"type":"→","content":"隻你也吃爽爽"}]},{"user":"LyoBei","replies":[{"type":"→","content":"棍棒敲擊法才不是那樣亂打一氣好嗎,起碼先固定狗四肢和頭"}]}]}