{"category":"新聞","title":"[新聞] 歐陽娜娜和緋聞男友同時曬甜笑照　網友","author":"kinki5566","content":"","pushes":[{"user":"iPhone4sW","replies":[{"type":"→","content":"CD"}]},{"user":"junki8957","replies":[{"type":"噓","content":"嗯"}]},{"user":"LyoBei","replies":[{"type":"噓","content":"她誰啊 我才不想管"}]},{"user":"alog","replies":[{"type":"→","content":"遺傳父母歐陽龍和傅娟的優良基因....what"}]},{"user":"gogobar","replies":[{"type":"噓","content":"長頭髮有奶子的歐陽龍 看了不舒服"}]},{"user":"watashiD","replies":[{"type":"噓","content":"居然用微博..."}]},{"user":"sigmaaldrich","replies":[{"type":"推","content":"娜娜是處女的機率？"}]},{"user":"san70168","replies":[{"type":"→","content":"我瓦力十足 想幹歐陽菲菲"}]},{"user":"ppu12372","replies":[{"type":"噓","content":"哪來的智障網友"}]},{"user":"tyrande","replies":[{"type":"推","content":"怎麼一臉韓國樣... 現在都流行這種的"}]},{"user":"liujackkl","replies":[{"type":"噓","content":"乾我們屁事"}]},{"user":"acergame5","replies":[{"type":"噓","content":"200給我就推"}]},{"user":"jajepound","replies":[{"type":"噓","content":"426網友吧"}]},{"user":"nepenthes7","replies":[{"type":"噓","content":"還真的一周一新聞 煩不煩"}]},{"user":"hank11235813","replies":[{"type":"噓","content":"哪來的網友? 精神病院來的嗎?"}]},{"user":"ange09","replies":[{"type":"噓","content":"垃圾新聞 他到底什麼咖"}]},{"user":"taurus512","replies":[{"type":"噓","content":"很討厭這家人 一直有新聞"}]},{"user":"mild7no1","replies":[{"type":"推","content":"射精^_^"}]},{"user":"HD0621","replies":[{"type":"噓","content":"真懷疑她有啥特權 又不紅 ，新聞卻一直報她"}]},{"user":"ByKiss","replies":[{"type":"噓","content":"5樓騙人 哪裡有奶"}]},{"user":"icespeech","replies":[{"type":"推","content":"比她姐姐正"}]},{"user":"dostey","replies":[{"type":"噓","content":"必噓!!!!!  歐陽xx,大小S,黑人夫婦,偉忠x,makiyo"}]},{"user":"thinkid","replies":[{"type":"噓","content":"歐陽妮妮穿外套意外發現200元"}]},{"user":"astroflyer","replies":[{"type":"噓","content":"掰"}]},{"user":"piovoso","replies":[{"type":"噓","content":"干我屁事"}]},{"user":"ev331","replies":[{"type":"→","content":"美國放假 真的新聞超多的"},{"type":"→","content":"她們家現在是不是全家都藝人?"}]},{"user":"withjusaka","replies":[{"type":"噓","content":"很煩"}]},{"user":"Murasaki0110","replies":[{"type":"噓","content":"14 好爽歐"}]},{"user":"fastmonster","replies":[{"type":"噓","content":"靠北噢 馬的干我屁事"}]},{"user":"CycleEnergy","replies":[{"type":"推","content":"聖誕節要到惹 是個能看的妹 我都會說可以"}]},{"user":"adc798","replies":[{"type":"推","content":"撿到兩百就可以無的放傘???"}]},{"user":"thbw666","replies":[{"type":"噓","content":"好討厭的鼻子"}]},{"user":"xxxd851130","replies":[{"type":"→","content":"好#"}]},{"user":"Comebuy","replies":[{"type":"噓","content":"撿到個男友"}]},{"user":"god4785","replies":[{"type":"噓","content":"喔。"}]},{"user":"Jackyfans","replies":[{"type":"噓","content":"甘我屁事"}]},{"user":"wolfking623","replies":[{"type":"噓","content":"醜"}]},{"user":"liuedd","replies":[{"type":"推","content":"快要過蘿莉賞味期了，難怪"},{"type":"→","content":"難過"}]},{"user":"SFlash","replies":[{"type":"噓","content":"歐陽龍把老本都砸在女兒身上"}]},{"user":"strikegundam","replies":[{"type":"噓","content":"我也想當議員"}]},{"user":"aidao","replies":[{"type":"噓","content":"不蘇胡"}]},{"user":"kyo2001","replies":[{"type":"噓","content":"哦"}]},{"user":"ppon","replies":[{"type":"噓","content":"干我屁事"}]},{"user":"aquariusx","replies":[{"type":"噓","content":"不送"}]},{"user":"drpotter6197","replies":[{"type":"噓","content":"…………"}]},{"user":"peterandwolf","replies":[{"type":"噓","content":"廢"}]},{"user":"azz778888","replies":[{"type":"噓","content":"我來"}]},{"user":"r107620966","replies":[{"type":"噓","content":"長得根本路人 比很多路人還普"}]},{"user":"tyrone126","replies":[{"type":"噓","content":"長的普通好嗎"}]},{"user":"angel3632005","replies":[{"type":"噓","content":"范建夫婦化？有夠礙眼的"}]},{"user":"sorrowly","replies":[{"type":"噓","content":"不想知道"}]},{"user":"cyrilpan","replies":[{"type":"噓","content":"她哪位？"}]},{"user":"kevin31a2","replies":[{"type":"噓","content":"這樣也行？是花多少給記者？"}]},{"user":"eatshit200","replies":[{"type":"噓","content":"百噓不厭"}]},{"user":"harrygp","replies":[{"type":"噓","content":"神女"}]},{"user":"augnusz","replies":[{"type":"推","content":"噓"}]},{"user":"prkfcpr","replies":[{"type":"噓","content":"牙齒白？"}]},{"user":"nogardercas","replies":[{"type":"噓","content":"2"}]},{"user":"aa58231","replies":[{"type":"噓","content":"閉嘴"}]},{"user":"shrekchang","replies":[{"type":"→","content":"啊~是滾床了沒？"}]},{"user":"violin3316","replies":[{"type":"噓","content":"呵呵"}]},{"user":"GsJames","replies":[{"type":"噓","content":"破處再報"}]},{"user":"micky5521","replies":[{"type":"噓","content":"簡體噓"}]},{"user":"redmool","replies":[{"type":"噓","content":"逢歐陽必噓"}]},{"user":"jonahlin","replies":[{"type":"噓","content":"她有紅嗎？長的又路人  她的上報率真的很莫名"}]},{"user":"ghgn","replies":[{"type":"噓","content":"乾我屁事"}]},{"user":"king12272","replies":[{"type":"噓","content":"別鬧了 兩白塊"}]},{"user":"SUZIKU","replies":[{"type":"噓","content":"噓噓樂"}]},{"user":"hyperionii","replies":[{"type":"噓","content":"老爸政績-炒女兒新聞，該選區選民智商真不簡單"}]},{"user":"stardoor","replies":[{"type":"推","content":"長的比姐姐漂亮多了"}]},{"user":"racas1201","replies":[{"type":"噓","content":"?"}]},{"user":"charlesyeh67","replies":[{"type":"噓","content":"喔。"}]},{"user":"canucksteve","replies":[{"type":"噓","content":"廢"}]},{"user":"q210216","replies":[{"type":"噓","content":"被中出懷孕再報吧！"}]},{"user":"cady69","replies":[{"type":"噓","content":"每日任務(1/1)"}]},{"user":"q152134","replies":[{"type":"推","content":"娜娜就要推"}]}]}