{"category":"新聞","title":"[新聞] 日本調查10大理想美胸F奶綾瀨遙大勝奪冠","author":"be98","content":"","pushes":[{"user":"iPhone4sW","replies":[{"type":"推","content":"好久沒露了"}]},{"user":"yunchukawai","replies":[{"type":"推","content":"深田溫泉那個早就被看光光"}]},{"user":"r107620966","replies":[{"type":"推","content":"http://gfycat.com/DeterminedAlarmedCaterpillar"}]},{"user":"asiakid","replies":[{"type":"推","content":"大隻馬"}]},{"user":"jerrys0580","replies":[{"type":"→","content":"Kate Upton:"}]},{"user":"ishiki","replies":[{"type":"→","content":"柏木KG"}]},{"user":"shwkz","replies":[{"type":"→","content":"壇蜜也kg"}]},{"user":"j73596","replies":[{"type":"→","content":"這...綾瀨遙沒有很巨吧?"}]},{"user":"t1520061217","replies":[{"type":"→","content":"F沒有很巨...?"}]},{"user":"sjack","replies":[{"type":"推","content":"綾瀨遙不巨?J7大是不是身邊肥婆太多了"}]},{"user":"tahikuro","replies":[{"type":"推","content":"為何沒有上戶彩 倉科加奈 真木陽子仲理依莎鈴木千奈美"}]}]}