{"category":"Re:","title":"Re: [問卦] 藥師對買廣告藥的人之心態","author":"nekoni","content":"\n有，有那種刻意仿冒普拿疼的包裝，一盒10顆、80元，完全無效\n\n\n到天龍國這種惡劣的地方後\n本魯幾乎都是把Acetaminophen當點心吃\n就算剝半吃，嚴重時每天要吃到三顆\n\nAcetaminophen很貴嗎？\n一點也不貴…\n\n「普拿疼」真的很貴，一盒10顆、100元\n各大醫院用的「力停疼」，一排10顆、20元，而且效果幾乎沒差，藥局就有賣\n\n健保給付藥費一天不到10元，怎麼可能用的起「普拿疼」？\n\n\n10顆20元，就算是魔法變出來的，成本不用錢，(mp藥水總要錢吧，補師總該要薪水吧)\n賣掉一排也才賺20元\n我一星期吃兩排好了，才賺我40元\n現在都時薪115了說，40元連便當都買不起\n\n--\n了解\n","pushes":[{"user":"turtleone","replies":[{"type":"推","content":"健保給付是算一顆給多少的"}]},{"user":"cloud72426","replies":[{"type":"噓","content":"不爽不要來啊"}]},{"user":"ManCity5566","replies":[{"type":"推","content":"力停疼一排15塊 第一次買時嚇到"}]},{"user":"piadora","replies":[{"type":"推","content":"各大醫院用的「力停疼」，一排10顆、20元....."},{"type":"→","content":"哪買的 我買一盒一排八顆 九十元"}]}]}