{"category":"問卦","title":"[問卦] 有沒有耶穌不是12/24生日的八卦","author":"arisa103","content":"\n有個教會的姐妹跟我說\n耶穌根本就不是冬天生的\n祂的生日也不是12/24\n所以他們的教會也不會慶祝耶誕節\n\n聽得我目瞪口呆\n有沒有耶穌不是12/24生的八卦嗎\n\n\n\n--\nSent from my Android\n\n--\n厲害！就是耶和華見證人  他們有什麼不好嗎\n","pushes":[{"user":"mimi1020b","replies":[{"type":"→","content":"我們只在乎耶穌什麼時候死"}]},{"user":"dnek","replies":[{"type":"推","content":"本來就是，聖誕節是太陽神的節日，達文西密碼都有說"}]},{"user":"beaver","replies":[{"type":"→","content":"1225是太陽節啦"},{"type":"→","content":"基督宗教本來就是靠這招快速傳教"}]},{"user":"tomx","replies":[{"type":"推","content":"聖誕節的時候就是汽車旅館跟夜店最受歡迎的時候"}]},{"user":"JeanSijhih","replies":[{"type":"→","content":"牽涉到曆法在羅馬時代的變革，猶太人本身的文化，以"},{"type":"→","content":"及聖經版本的問題"},{"type":"→","content":"認真研究你會發現人類文明有多少約定成俗的商業騙局"}]},{"user":"larailing","replies":[{"type":"推","content":"24號叫平安夜 25號才是耶穌生日"}]},{"user":"kasion","replies":[{"type":"→","content":"菜"}]},{"user":"raichu312","replies":[{"type":"→","content":"那天生日是人為自己訂的，確切日期實為不詳。"},{"type":"→","content":"應該是真耶穌教會吧"}]},{"user":"future314","replies":[{"type":"→","content":"其實耶穌也不是在西元元年出生的"}]},{"user":"disc01","replies":[{"type":"→","content":"耶和華見證人嗎 聽聽就好"}]},{"user":"nakayamayyt","replies":[{"type":"→","content":"那他們為甚麼不在24號慶祝 這理由超鳥的"}]},{"user":"FlynnZhang","replies":[{"type":"推","content":"干我屁事"}]},{"user":"nixon","replies":[{"type":"→","content":"24號要去報佳音"}]},{"user":"BlacKlonely","replies":[{"type":"推","content":"24號要吃大餐晚上和妻辣修幹"}]},{"user":"IvanLord","replies":[{"type":"噓","content":"這與耶和華見證人有毛關係？難道路德會.長老教會說的也"},{"type":"→","content":"不算就是？本來就是人訂的"}]}]}