{"category":"Re:","title":"Re: [爆卦] 實拍中國的殺狗工廠(血腥慎入)","author":"tropotato","content":"\n\n好啦，我來回答你\n\n經過我長期看過動寶團體跳針（說跳真是因為不管怎樣做，洞寶都說處理方式未達標。擺\n明叫大家去吃素）的論述：\n\n1.影片中叫聲四起，待屠的狗會怕怕\n\n2.狗屍遍佈，待屠的狗看到會怕怕（狗看不看的懂又是另一回事\n\n3.環境髒亂，狗隻沒有良好的生活環境\n\n請問動保們以上是否正確\n\n\n\n不過我是覺得影片中用棒擊還算人道，不過觀感不佳，就像加拿大獵海豹一樣\n\n--\n因為用傳統冷兵器擊暈不是用高科技電暈,所以看來比較殘暴比較low\n你沒講我還沒注意=_=，真的在馬路旁......真的有夠天\n那麼想吃人肉可以去日本，上次有藝術家賣屌給人吃。 不過我建議不要吃，要不每天走\n在路上看到正妹就要猜測她好不好吃......\n","pushes":[{"user":"lookyour","replies":[{"type":"→","content":"你應該還要說他們是在馬路旁人來人往殺狗，而不是巷弄裡"},{"type":"→","content":"最後那個畫面就是在馬路旁...就算是豬，也沒人會在路旁"},{"type":"→","content":"八皮吧...2樓麻煩再去看看"}]},{"user":"goodjeff","replies":[{"type":"推","content":"我比較好奇哪有什麼觀感不佳 又不是在戶外表演"},{"type":"→","content":"還真的 我沒看完 因為有點想吐"}]},{"user":"wotupset","replies":[{"type":"推","content":"把狗代換成其他動物 動保也會靠北"}]},{"user":"DaiRiT","replies":[{"type":"噓","content":"那快人道宰殺人肉  吃人肉叉燒包阿"},{"type":"→","content":"死刑犯拿來人道宰殺作料理不違法吧"},{"type":"→","content":"人→違法  狗→合法"},{"type":"→","content":"太棒了"}]},{"user":"arrenwu","replies":[{"type":"推","content":"殺人犯法啊"},{"type":"推","content":"犯法啊，沒當事人同意的連死刑犯的器官都不能拿去器捐"}]},{"user":"bobju","replies":[{"type":"→","content":"就像在大街上晾衣服一樣, 很慘 /_\\"}]},{"user":"q5228859","replies":[{"type":"推","content":"別為反而反 宰雞場也沒那麼噁爛好嗎"}]},{"user":"acgotaku","replies":[{"type":"→","content":"如果狗有地獄,應該就像影片那樣 不會有更慘的地方了"}]},{"user":"tgsh","replies":[{"type":"推","content":"青菜植物不會慘叫衰小給你吃"}]},{"user":"ForeverDaivd","replies":[{"type":"噓","content":"為反而反? 寂寞要人陪就說出來不會有人笑你"}]}]}