{"category":"Re:","title":"Re: [爆卦]Costco台南店請病假很難嗎？當事家庭的控訴","author":"thatislife","content":"\n事件回顧：\n當事人丈夫臉書首PO      2014/12/17 16：06\n\n\nPTT我的發文             2014/12/20  00:44:\n\n\n\n最新動態：\n            2014/12/20 不知道時辰與公告地點\n\n\n         2014/12/21  2:55\n\n\n\n\n\n  我跟當事家庭並無直接認識，但有共同朋友A，A12/19深夜在FB分享這件事，\n  個人搜尋網路沒有這件事的任何資訊可參考。A說可以公開分享。\n\n  所以我自行整理貼於PTT，貼了才告知A請他轉告李先生。\n\n  今天A說:「李先生表示感謝鄉民提供的建議和支持，\n  李先生發現Costco有紙本公告張貼，再提出說明希望我也幫忙貼出。」\n\n  我查了Costco網頁與今天的新聞並沒有相關訊息，也不了解聲明內容\n  基於資訊公開公平原則請他提供好市多的聲明，兩造說法並覽。\n\n  感謝PTT八卦版的關注，\n  讓Costco迅速有台灣區營運副總經理簽名的(公開？)紙本回應\n\n--\n","pushes":[{"user":"BirthdayBoy","replies":[{"type":"推","content":"'幫高調"}]},{"user":"joseph0318","replies":[{"type":"→","content":"當然不起訴你們公司啊 法人又不是刑法對象"}]},{"user":"coyoteY","replies":[{"type":"推","content":"加油!自己的勞工自己救"}]},{"user":"Fiona102","replies":[{"type":"推","content":"全力抵制摳屎摳 馬上剪卡   但是還是有去摳屎摳買林鳳營"},{"type":"→","content":"的XX 助長這些企業成長"}]},{"user":"kutkin","replies":[{"type":"推","content":"看起來是12/4告不成  就轉而訴諸輿論"}]},{"user":"h70575","replies":[{"type":"推","content":"高調"}]},{"user":"NigoMax","replies":[{"type":"推","content":"副總簽名? 顆顆 代總經理嗎?"}]},{"user":"monismile","replies":[{"type":"推","content":"幫高調"}]},{"user":"w603210326","replies":[{"type":"推","content":"高調"}]},{"user":"wattswatts","replies":[{"type":"→","content":"智慧型手機不是拿來玩遊戲的，你知道該怎麼做吧！"}]},{"user":"jhc0723","replies":[{"type":"推","content":"這種去美國打官司才對  costco才會怕.."}]}]}