{"category":"問卦","title":"[問卦] 有沒有PTT誤我一生的八卦","author":"iXXXXGAY5566","content":"\n本魯當初蒙董無知 踏入了ptt 這個比演藝圈 還要色色的大染肛\n\n一開始去sex版 覺得每篇文章的怎麼都這麼淫蕩\n\n看著標題 就不爭氣的ggininderrrrrrrrrrrrrrrrrrr\n\n人生 愛情 事業 全部荒廢 只剩ptt\n\n馬的 ptt 怎麼這麼好戒 我每個禮拜都想著戒\n\n每個禮拜 又在懊惱 一直上ptt\n\n喔 對了 lovechen239 走啦走啦 去吃宵夜拉\n\n\n\n\n\n\n\n\n\n\n\n\n\n\n\n\n\n\n\n\n\n\n\n\n\n\n\n\n\n\n反正瘦不下去了\n\n--\n慢了五分鐘 還自婊 你是故意要引起我的注意嗎\n幹 你好關心我唷 跟我已結婚為前提交往巴  *.<\n","pushes":[{"user":"HuangXueyong","replies":[{"type":"→","content":"幹 我好想哭"}]},{"user":"Benbenyale","replies":[{"type":"→","content":"五樓玩ptt到沒錢要賣屁股"}]},{"user":"wuyiulin","replies":[{"type":"噓","content":"你荒廢關我屁事"}]},{"user":"HiJun","replies":[{"type":"推","content":"蓋"}]},{"user":"Athemase","replies":[{"type":"噓","content":"5樓屁股賣給4X"}]},{"user":"KEKEKUO","replies":[{"type":"噓","content":"連三篇呢?"}]},{"user":"maxlin9527","replies":[{"type":"→","content":"ip"}]},{"user":"freeway56","replies":[{"type":"推","content":"可以不要說我了嗎？"}]},{"user":"zhankai","replies":[{"type":"噓","content":"廢文"}]},{"user":"tpn","replies":[{"type":"噓","content":"http://i.imgur.com/FbIXNQg.jpg"}]},{"user":"dostey","replies":[{"type":"噓","content":"XD.這隻中毒太深, 沒救了"}]},{"user":"a09374567","replies":[{"type":"噓","content":"這樣就IN..."}]},{"user":"milk0513","replies":[{"type":"噓","content":"抱歉lovechen我的"}]},{"user":"lkrichard","replies":[{"type":"推","content":"居然趁機搭訕乳肥"}]}]}