{"category":"新聞","title":"[新聞] 44歲以下的上班族　你的名字叫「洋蔥」","author":"LeonaxIori","content":"","pushes":[{"user":"MuscleMan","replies":[{"type":"推","content":"一層一層一層"}]},{"user":"XieXie9527","replies":[{"type":"→","content":"如果你願意一層一層一層的剝開我的心"}]},{"user":"cpc21478","replies":[{"type":"推","content":"你會發現"}]},{"user":"cattgirl","replies":[{"type":"推","content":" 馬政府舉債破24兆  台灣沒救了"}]},{"user":"mvpdirk712","replies":[{"type":"→","content":"              撥開我的心"}]},{"user":"BF109Pilot","replies":[{"type":"推","content":"洋蔥騎士"}]},{"user":"twod758","replies":[{"type":"推","content":"                   砰呀阿喔呀唷             o'_'o"}]},{"user":"suhaw","replies":[{"type":"→","content":"恩 我覺得楊宗緯翻唱阿信的歌唱得不錯"}]},{"user":"Chia2323","replies":[{"type":"推","content":"你會發現 你會訝異"}]},{"user":"apa9394","replies":[{"type":"推","content":"你會發現 你會流淚"},{"type":"→","content":"洋蔥騎士一開始就可以練 砍24刀 99999"}]},{"user":"t1329kimo","replies":[{"type":"推","content":"還好我有做房東剝魯蛇"}]},{"user":"tchialen","replies":[{"type":"推","content":"都是上一輩老屁股害的"}]},{"user":"dogisburning","replies":[{"type":"推","content":"嗚嗚我們好可憐"}]},{"user":"deepdish","replies":[{"type":"推","content":"KMT立委 不過就是既得利益的傳聲筒 毫無中心價值可言"}]},{"user":"BaGaJohn","replies":[{"type":"推","content":"234樓害我笑了"}]},{"user":"Leeng","replies":[{"type":"噓","content":"這又這些名詞到底是誰叫的??"}]},{"user":"mxr","replies":[{"type":"推","content":"錢都被財團拿走了 然後牠們的下一代繼續剝削我們"}]},{"user":"cul287","replies":[{"type":"推","content":"被剝削感是很痛苦的"}]},{"user":"purplvampire","replies":[{"type":"推","content":"小英：國內重要政治人物不宜這時表態"}]},{"user":"TommyYuen","replies":[{"type":"推","content":"伊呀伊呀"}]},{"user":"josh17","replies":[{"type":"推","content":"一般的上班族現在買房子等於簽下被奴役契約"}]},{"user":"vdml","replies":[{"type":"推","content":"7年級出社會幾年好不容易存點錢 就又丟到房債高點裡"}]},{"user":"bce","replies":[{"type":"→","content":"選出了馬英九,還讓他連任,這到底要怪誰?"}]},{"user":"simata","replies":[{"type":"推","content":"怒"}]},{"user":"EFPTT","replies":[{"type":"推","content":"洋蔥鄉民"}]},{"user":"kingcallme","replies":[{"type":"推","content":"所以2016誰上都賽缺，除非有種終極統一讓老共概括承受"}]},{"user":"hoho0505","replies":[{"type":"→","content":"不懂為何中共要承受這些 到時 都砍掉不就好了"},{"type":"→","content":"對中共來說 這只是內政問題 國際間簽署的都能說廢就廢"},{"type":"→","content":"何必要承擔台灣未來退休的費用或福利~~"}]},{"user":"scott032","replies":[{"type":"推","content":"房子賣這麼貴 又沒退休金 有夠衰小的"}]},{"user":"kixer2005","replies":[{"type":"噓","content":"幹你娘的  我要去豪宅的公共空間騎腳踏車示威"}]},{"user":"Jwhat","replies":[{"type":"推","content":"推簽名檔"}]},{"user":"brycejack","replies":[{"type":"推","content":"每個人都穿一套洋蔥騎士"}]},{"user":"c7683fh6","replies":[{"type":"推","content":"推北美智權報"}]},{"user":"satyrs05","replies":[{"type":"推","content":"終極統一，你覺得新台幣會怎麼換人民幣? 不敢再想下去"}]},{"user":"codehard","replies":[{"type":"推","content":"到時還有4萬新台幣換一元新新台幣絕招 別怕"}]},{"user":"oops66","replies":[{"type":"推","content":"是洋蔥 我加了洋蔥"}]}]}