{"category":"問卦","title":"[問卦] 辛普森家庭的梗","author":"GuanWei0709","content":"\n小魯現在家裡收看MOD，轉到FOX HD台正在播映辛普森家庭，發現有些梗實在太鄉民梗惹\n，請問各位鄉民知道裡面的編輯台詞都是哪版的鄉民梗，我猜就是八卦版吧？\n\n 八卦板務請到              檢舉板詢問\n   張貼問卦請注意，內容是否過少，是否有專板，本板並非萬能問板。\n   一天只能張貼  兩則  問卦，自刪及被刪也算兩篇之內，\n   超貼者將被劣文，請注意\n   本看板嚴格禁止政治問卦，發文問卦前請先仔細閱讀相關板規。\n  ↑看完提醒可刪除\n\n\n--\nSent from my Android\n\n--\n","pushes":[{"user":"lunqun35","replies":[{"type":"推","content":"現在都重播的....等待買新的中"}]},{"user":"newsnew","replies":[{"type":"→","content":"西斯梗也常出現"}]},{"user":"chlechin","replies":[{"type":"噓","content":"連糞文 是你？"}]},{"user":"qwqwaas","replies":[{"type":"→","content":"亂翻一通吧 都看圖說故事 也不是真的翻譯"}]},{"user":"haniah","replies":[{"type":"推","content":"亂翻一通+1"}]},{"user":"benson8389","replies":[{"type":"→","content":"紐約翻成信義區"}]},{"user":"vin850411","replies":[{"type":"推","content":"直接翻其實你也不知道是什麼梗"}]},{"user":"hotqqa","replies":[{"type":"推","content":"鴿子封包到了喔"}]},{"user":"k66110011","replies":[{"type":"推","content":"反台灣翻譯者甚麼都要直翻才爽"}]},{"user":"bjj","replies":[{"type":"推","content":"在地化翻譯"}]},{"user":"Pietro","replies":[{"type":"→","content":"停播黑棒 還我南方"}]},{"user":"HinataME","replies":[{"type":"推","content":"孤單蒼老的靈魂，正在尋找人生最後一座斷背山"}]},{"user":"asiaking5566","replies":[{"type":"推","content":"之前播映  沒在地化翻譯時比較好笑"}]},{"user":"arceus","replies":[{"type":"推","content":"梗&語調都不錯"}]},{"user":"crea0520","replies":[{"type":"→","content":"一定是鄉民啊，超有趣的"}]},{"user":"ohmyya","replies":[{"type":"→","content":"覺得好笑就好"}]},{"user":"fastmonster","replies":[{"type":"推","content":"梗用過頭 有點難笑"}]},{"user":"frey","replies":[{"type":"推","content":"有點硬湊，後來覺得有點無聊。"}]},{"user":"rainet","replies":[{"type":"推","content":"楚魚"}]},{"user":"qwaszx1793","replies":[{"type":"推","content":"臺灣有臺灣的玩法"}]},{"user":"Wafter","replies":[{"type":"推","content":"辛普森殺妻案"}]},{"user":"mvpjalen","replies":[{"type":"→","content":"記得之前東森好像也播過,當時的翻譯好太多了"},{"type":"→","content":"不只是照故事內容翻,還能融入台灣的時事"}]}]}