{"category":"新聞","title":"[新聞] 推廣「南半球」之美 日興起《下乳協會》","author":"Susan45","content":"","pushes":[{"user":"colorbest","replies":[{"type":"→","content":"我..."},{"type":"→","content":"我忍不住了....三樓快來吸"}]},{"user":"tom0407","replies":[{"type":"推","content":"未看先猜樓下馬奶圖"}]},{"user":"coon182","replies":[{"type":"→","content":"猜錯了"}]},{"user":"yoyodiy","replies":[{"type":"→","content":"樓下馬奶圖"}]},{"user":"al1l1","replies":[{"type":"推","content":"脾氣兇不好嗎"}]},{"user":"linzero","replies":[{"type":"→","content":"赤道比較好看"}]},{"user":"w180112","replies":[{"type":"推","content":"五樓專門吸馬奶"}]},{"user":"cysh0621","replies":[{"type":"推","content":"召喚西斯a圖王"}]},{"user":"Forcegerm","replies":[{"type":"推","content":"這麼晚你給我看這個"}]},{"user":"u6vmp1756","replies":[{"type":"推","content":"樓下馬奶"}]},{"user":"shields5566","replies":[{"type":"推","content":"忍不住了 只好看馬奶消火"}]},{"user":"stock0907","replies":[{"type":"推","content":"南半球推雞排妹快去投票圖"}]},{"user":"tuansam","replies":[{"type":"推","content":"http://i.imgur.com/YfunOia.jpg 這南半球 我可以"}]},{"user":"shintz","replies":[{"type":"推","content":"http://i.imgur.com/WVgS33k.jpg 南半球"}]},{"user":"bernon","replies":[{"type":"推","content":"你們到底是有多愛馬英九"}]},{"user":"ufo15526368","replies":[{"type":"推","content":"tuansam 那張很正點 www"}]},{"user":"tn00210585","replies":[{"type":"推","content":"乳袋才是正道   好嗎"}]},{"user":"willy4409","replies":[{"type":"推","content":"極東支部  アリサ　俺の嫁　以上"}]},{"user":"siamese","replies":[{"type":"→","content":"下乳 用隆的就做的出來了"}]}]}