{"category":"新聞","title":"[新聞] 雙北安養機構 9成2拒愛滋感染者入住","author":"Sargasso","content":"","pushes":[{"user":"cutbear123","replies":[{"type":"推","content":"Fags"}]},{"user":"blmp1234","replies":[{"type":"→","content":"聽說不是FAG 不能用FAG這個字XD"}]},{"user":"otld","replies":[{"type":"推","content":"畢竟照顧不好的話說不定會讓整間安養院的人都中標"}]},{"user":"alog","replies":[{"type":"推","content":"安養的衛生或環境條件沒有你想像中的好"},{"type":"→","content":"他們自己心裡有數 當然拒絕"},{"type":"→","content":"或許愛滋患者沒問題 但其他人會恐懼"},{"type":"→","content":"還有在哪裡的人會沒事找事做 有些人會被針對"}]},{"user":"pchan5231","replies":[{"type":"噓","content":"噓備註"}]},{"user":"askingts","replies":[{"type":"推","content":" 推備註"}]},{"user":"k33536","replies":[{"type":"推","content":"推備註"}]},{"user":"MacOSX10","replies":[{"type":"→","content":"愛滋會可以自己去開一家啊 幹嘛只在那邊講"},{"type":"→","content":"這又不是像核廢料發的電每個人都有爽到"},{"type":"→","content":"那些人自己要負責啊"}]},{"user":"john50710","replies":[{"type":"噓","content":"好棒棒"}]},{"user":"shwkz","replies":[{"type":"→","content":"拒絕同性戀"}]},{"user":"bobobola","replies":[{"type":"推","content":"歧視甲甲"}]},{"user":"IOP14759","replies":[{"type":"推","content":"不想被歧視就別得艾滋阿，愛互肛又不帶套，自找的"}]},{"user":"izna","replies":[{"type":"推","content":"有些是老婆被自己老公傳染的 還有垂直感染和輸血感染"},{"type":"→","content":"以前有過病患拿著裝著自己血液的針筒在鬧區亂戳"}]},{"user":"Hambowbow","replies":[{"type":"推","content":"92共識"}]}]}