{"category":"問卦","title":"[問卦] 嘉義縣和基隆市人口結構失衡特別嚴重","author":"changnick502","content":"\n內政部戶政司的人口總計資料\n\n         總計     0 ~ 4歲    0 ~ 6歲    0 ~ 11歲   0 ~ 12歲   65歲以上 十年相比\n\n嘉義縣  525,579    3.01%      4.28%      8.20%      9.19%      16.80%   \n                 (倒數第二) (倒數第二) (倒數第一) (倒數第一) (全台最高)\n\n基隆市  373,340    2.85%      4.24%      8.33%      9.29%      12.48%   \n                 (倒數第一) (倒數第一) (倒數第二) (倒數第二)\n\n\n不是作業文\n\n但有沒有這兩個地方\n\n人口年齡結構失衡特別嚴重的八卦\n\n\n--\n","pushes":[{"user":"kutkin","replies":[{"type":"推","content":"沒工作  不過台北市...你也可看看"},{"type":"推","content":"台北也是13% 65+"}]},{"user":"railman","replies":[{"type":"推","content":"每次一到基隆就彷彿在東南亞般的感覺"}]},{"user":"d9637568","replies":[{"type":"推","content":"省轄市剩下新竹苟延殘喘"},{"type":"推","content":"基隆當初成為省轄市因為港口 嘉義是輸送阿里山樹木據點"},{"type":"→","content":"不過現在看來就沒有意義了"},{"type":"→","content":"當年台中市台南市成為直轄市就差不多要廢掉省轄市了"}]},{"user":"YishengSu","replies":[{"type":"→","content":"中永和最多烏合之眾(戰)"}]},{"user":"Kobeeeee5566","replies":[{"type":"推","content":"基隆天氣時常不好"}]},{"user":"cysh0621","replies":[{"type":"推","content":"嘉義都被426佔領了"}]},{"user":"v3aa7n","replies":[{"type":"→","content":"別再嗆我們了啦Q_Q"}]},{"user":"MMMB4219","replies":[{"type":"噓","content":"嘉義真悲哀"}]},{"user":"lilychichi","replies":[{"type":"推","content":"其實有些住基隆的人 戶籍可能在台北 因為補助跟福利…"}]}]}