{"category":"Re:","title":"Re: [問卦] 有沒有台大學生大多是權貴的八卦","author":"bewealthy","content":"\n\n忽然想到一件關於這個的八卦\n\n那就是台大學生很不喜歡聽到這類話題\n\n通常他們都會搶著澄清：「我不有錢呀」\n\n「你自己念不來怪我囉」\n\n「難道我只是有錢，不讀書就能考上嗎？」等等諸如此類的問題\n\n\n台大學生總的來說對這件事還滿心胸狹窄的\n\n\n--\n","pushes":[{"user":"ppder","replies":[{"type":"→","content":"ip正確"}]},{"user":"sagarain","replies":[{"type":"→","content":"剩文也這樣說"}]},{"user":"deangogi","replies":[{"type":"→","content":"我的富二代同學每隔幾個月就要去日本long stay一下"}]},{"user":"lolic","replies":[{"type":"→","content":"事實就是有錢比較可以專心念書阿"}]},{"user":"yayahappy96","replies":[{"type":"推","content":"很多人從小補英文就很有優勢了"},{"type":"→","content":"不少科系都加權英文"}]},{"user":"abs7862604","replies":[{"type":"推","content":"放心現在還好，免試入學未來更多"}]},{"user":"chogosu","replies":[{"type":"推","content":"因為很多人以為靠自己就可以上台大,沒意識到也有幸運成份"}]},{"user":"ADHD","replies":[{"type":"推","content":"真的就是這樣"}]}]}