{"category":"問卦","title":"[問卦] 請問知音時間的八卦?","author":"kintesobad","content":"\n       中廣流行網-羅小雲的知音時間，是以前家喻戶曉的廣播電台\n       每週都有流行音樂排行榜，以下是我記得上過前幾名的歌跟歌手\n\n       1.忘情水-劉德華\n       2.執迷不悔-王靖雯\n       3.為情所困-梁朝偉\n       4.抱緊一點-堂娜\n       5.祝福-張學友\n       6.背包-蘇有朋\n       7.溫柔超人-金城武\n       8.對你的愛永遠多一點-黎明\n       9.夢醒時分-陳淑樺\n      10.向太陽怒吼-王傑\n      11.情願是你讓我心傷-何雨雯 (現改名何妤玟)\n\n       沒錯!何雨雯那時以中山女高學生清純的模樣\n       剛出道的歌:情願是你讓我心傷，還拿過排行榜冠軍幾週！！\n       印象中還聽到是:成功高中全力支持...(這..?)\n       請問那時候的排行榜是怎麼計票的? 聽眾該不會都是國高中生吧？\n       請問有什麼八掛嗎?\n\n--\n","pushes":[{"user":"melzard","replies":[{"type":"推","content":"我難過"}]},{"user":"justice00s","replies":[{"type":"→","content":"初音時間"}]},{"user":"nowhereman","replies":[{"type":"推","content":"20年前的回憶   一轉眼........都要30歲了"}]},{"user":"sagarain","replies":[{"type":"→","content":"你說你是隻鷹 樓下接唱"}]},{"user":"ClubT","replies":[{"type":"→","content":"軟體時間"}]},{"user":"Leeng","replies":[{"type":"噓","content":"不過是個軟體"}]},{"user":"akbobo","replies":[{"type":"推","content":"寄明信片。一張明信片可以寫5首歌,每週統計一次。"}]},{"user":"thirteenflor","replies":[{"type":"推","content":"最強第一名 伍思凱 愛到最高點"},{"type":"→","content":"蟬聯20幾周第一名 那時候的中華民國還未亡~~~~~"},{"type":"推","content":"https://www.youtube.com/watch?v=Xc2hY-tUHkk"}]},{"user":"masanini","replies":[{"type":"推","content":"羅小雲報榜速度超快。第一週進榜就第一名：永遠不回頭。"}]},{"user":"cooleagles","replies":[{"type":"推","content":"羅小雲後來好像跳槽去台北之音"}]}]}