{"category":"問卦","title":"[問卦] 有沒有56神曲很少的八卦","author":"s940255880","content":"\n大家唯一想到的神曲只有我難過\n\n反觀其他樂團\n\n五月天，魔幻力量，信樂團\n\n神曲多到十根手指頭都數不完\n\n有沒有56創造的神曲很窮酸的八卦\n\n--\nSent from my Android\n\n--\n","pushes":[{"user":"xyz4594","replies":[{"type":"→","content":"這篇推文沒有我難過  我就讓4X貓肛到哭出來為止"}]},{"user":"BlueBird5566","replies":[{"type":"噓","content":"神曲不需要靠多數來撐"}]},{"user":"YuenYang5566","replies":[{"type":"→","content":"我不難過"}]},{"user":"changwayway","replies":[{"type":"→","content":"我上過"}]},{"user":"Rondo5566","replies":[{"type":"噓","content":"神曲一首就夠"}]},{"user":"yua30507","replies":[{"type":"噓","content":"你的56id呢"}]},{"user":"kingaden","replies":[{"type":"推","content":"我楠過"}]},{"user":"XDDDDDDDDDDD","replies":[{"type":"推","content":" xyz4594: 這篇推文沒有我難過  我就讓4X貓肛到哭出"}]},{"user":"Colantoni","replies":[{"type":"推","content":"十根手指頭比不上一根屌"}]},{"user":"SpecX","replies":[{"type":"→","content":"我難媧"}]},{"user":"linceass","replies":[{"type":"→","content":"還有無所謂啊"}]},{"user":"jimmmy","replies":[{"type":"噓","content":"5566 我楊過"}]},{"user":"lovetina","replies":[{"type":"→","content":"我難過無所謂一光年"}]},{"user":"w328065","replies":[{"type":"推","content":"我被過"}]},{"user":"heiheidog","replies":[{"type":"噓","content":"4X貓還不想肛你呢！拿玩具自己來吧"}]},{"user":"Chia2323","replies":[{"type":"噓","content":"誰說的 無所謂 愛情漫遊 存在 風雲變色 放手一搏。好久"},{"type":"→","content":"不見都是神曲啊"}]},{"user":"kacatru","replies":[{"type":"噓","content":"我肛過"}]},{"user":"JuiFu617","replies":[{"type":"→","content":"I am sad"}]},{"user":"coldplay5566","replies":[{"type":"噓","content":"我難過"}]},{"user":"CHIMEI5566","replies":[{"type":"噓","content":"56ID呢?  我艱過"}]},{"user":"diefox","replies":[{"type":"推","content":"我硬過"}]},{"user":"dryad5566","replies":[{"type":"推","content":"你的56id勒"}]},{"user":"otsuka123","replies":[{"type":"推","content":"守候"}]},{"user":"A19870720","replies":[{"type":"→","content":"一首歌就撐到現在了 多幾首地球會爆"}]},{"user":"Rocks5566","replies":[{"type":"噓","content":"你的56ID勒"}]},{"user":"iWatch5566","replies":[{"type":"→","content":"我難濄"}]},{"user":"v0920516067","replies":[{"type":"→","content":"沒56id噓你"}]},{"user":"jack020408","replies":[{"type":"噓","content":"沒56ID不准發56文 讓我們替偉大的5566致敬"}]},{"user":"simonxarrow","replies":[{"type":"噓","content":"沒56ID也敢問56？"}]},{"user":"xman262","replies":[{"type":"推","content":"魔幻力量是啥屁 這也拿來跟56比?"}]}]}