{"category":"Re:","title":"Re: [問卦] 如果 1949 KMT 沒來我國？","author":"BruceLin","content":"\n看了一系列的奇文\n\n哥還是忍不住想發文 糾正已上的錯誤\n\n先談日本\n\n日本二戰結束 所有的資源 石油 鋼鐵 全部用光\n\n而且已經被打成黑暗時代 這個時候會有能力 管你台灣被共產黨接收?\n\n美國方面\n\n更可笑 還在那邊講 美國不會讓中共攻下台灣\n\n國共內戰 美國就已經放棄國民黨了 整片中國997/1000的領土不管\n\n還會來在意 整片中國3/1000的台灣 美國說穿了 只是給你一點美援\n\n讓蔣介石的政權不要倒 利用中國台灣內部的矛盾 從中獲利罷了\n\n真的為了台灣 跟中共對幹 那是不可能的\n\n\n總之結論 幸好國民黨有來 不然我們現在都是堂堂正正的中國人\n\n南無阿彌陀佛 哈勒嚕亞 讚嘆主 感恩主\n\n\n\n--\nSent from my Android\n\n--\n","pushes":[{"user":"jimmyoic","replies":[{"type":"→","content":"這個版的邏輯不就是 KMT消失 一切都相當美好嗎"}]},{"user":"tiuseensii","replies":[{"type":"→","content":"XD"}]},{"user":"query","replies":[{"type":"→","content":"錯 KMT沒來 台灣與澎湖就是UN接管 再交給日本或獨立"},{"type":"→","content":"支那共黨一點理由都沒有來攻打台灣"}]},{"user":"kaoru1992","replies":[{"type":"噓","content":"國民黨來了還是中國人好嗎"}]},{"user":"deepdish","replies":[{"type":"噓","content":"可憐 只能用幻想自慰"}]},{"user":"bmmbmmbmm","replies":[{"type":"噓","content":"杜魯門: 他們一家都是賊! 是賊! 是賊!"}]},{"user":"steve17","replies":[{"type":"噓","content":"吱吱都用夢想自慰阿 有夢最美 精液相隨"}]},{"user":"gogobar","replies":[{"type":"推","content":"以當時情況,被解放不見得是壞事"}]},{"user":"scott032","replies":[{"type":"噓","content":"這個ID不用看就知道要噓了XD"}]},{"user":"serval623","replies":[{"type":"噓","content":"看ID只能噓了"}]},{"user":"linkin5566","replies":[{"type":"噓","content":"id"}]},{"user":"peterwww","replies":[{"type":"推","content":"連被解放不是壞事都說出來了"},{"type":"→","content":"泛綠真的讓人無言  洗腦洗超級徹底"},{"type":"→","content":"討厭兩蔣幾乎可以仇恨式選擇性記憶"},{"type":"推","content":"很痛心  有人受到影響  這些帶風向是國家內賊"},{"type":"→","content":"阿扁八年真的改變很多  教育徹底去中國化"},{"type":"→","content":"要你傷害自己  你真的傻傻去做  皮下注射也不那麼快"},{"type":"推","content":"生命會懲罰的  傷害國家別人者必是先傷害自己"},{"type":"→","content":"政黨凌駕國家  企圖顛覆國家 背叛國家亦然"},{"type":"→","content":"寫得太正式  人家說你不近人情 就是忘國家恩"},{"type":"噓","content":"我是中國人  不可能被泛綠帶風向"},{"type":"→","content":"抱歉  推"}]},{"user":"chachameow","replies":[{"type":"噓","content":"誰跟你中國人 你他媽的噁不噁心"}]},{"user":"onlyhuman","replies":[{"type":"噓","content":":"}]},{"user":"benson502","replies":[{"type":"噓","content":"辛苦了"}]},{"user":"touchbird","replies":[{"type":"推","content":"台灣人可以打獨立戰爭阿!"}]},{"user":"a001223","replies":[{"type":"噓","content":"幸好KMT有來這種言論都說得出來 有夠可悲"}]},{"user":"as795132000","replies":[{"type":"噓","content":"...."}]}]}