{"category":"Re:","title":"Re: [新聞] 綠委：杯葛迫於無奈 相信人民會覺醒","author":"littlehero","content":"\n\n依照法律的標準，「行政命令」的前提是法律賦予政府此項裁量權\n\n如果有這項法律，以行政命令來要求國民黨歸環黨產當然是合理的。\n\n如果沒有，自然是濫權。\n\n而服貿通過的內容沒有超過WTO承諾\n\n早就在當初WTO協議國內法化時，就已經給予行政機關裁量權了\n\n這是和黨產條例的不同之處。\n\n事實上，這個不同之處也不難，絕大多數的版友都有能力分辨\n\n差別只在「想不想分辨」。\n\n要證明民進黨的雙重標準實在是多此一舉\n\n但既然民進黨選贏了，表示人民支持民進黨的雙重標準\n\n我也沒什麼意見。\n\n總之，民主政治就是民意至上\n\n多數民意做了決定少數就服從\n\n至於多數民意是不是正確的，等到民進黨執政就可以知道了。\n\n--\n","pushes":[{"user":"LaPass","replies":[{"type":"推","content":"多數民意做了決定少數就服從 <= 例如納粹的授權法?"}]},{"user":"Daz2005i","replies":[{"type":"噓","content":"民主的價值是自由人權 民意至上是民粹"}]},{"user":"h70575","replies":[{"type":"噓","content":"嗯。"}]},{"user":"ko007x","replies":[{"type":"→","content":"多數民意要殺光同性戀 那同性戀該殺嗎?"}]},{"user":"ziff","replies":[{"type":"推","content":"還沒崩潰完啊。"}]},{"user":"tkucuh","replies":[{"type":"→","content":"一堆人被釣了...小英雄耶。"}]},{"user":"WilliamWill","replies":[{"type":"推","content":"多數民意認為不是民粹，是民粹嗎？"}]},{"user":"demonh311","replies":[{"type":"推","content":"沒關系 反正2016我們kmt還是立委過半"}]},{"user":"BruceLin","replies":[{"type":"噓","content":"你講了實話 按照八卦板傳統 只好噓了 抱歉"}]},{"user":"ienari","replies":[{"type":"噓","content":"此ID必噓"}]},{"user":"alan5","replies":[{"type":"噓","content":"阿不就在承認多數民意給kmt搞是不正確的  崩潰完沒啊"}]},{"user":"lowc","replies":[{"type":"噓","content":"...最好民主是服從多數就好 是不知道尊重少數的重要嗎?"},{"type":"→","content":"你只是在崩潰 發洩情緒而已"}]},{"user":"jerry78424","replies":[{"type":"噓","content":"KMT不懂得尊重少數，所以少數就成了多數"}]},{"user":"angelliao37","replies":[{"type":"噓","content":"咀咀一路崩潰到2016吧！"}]},{"user":"cttw19","replies":[{"type":"噓","content":"還在崩潰哦XDDDD"}]},{"user":"biostar","replies":[{"type":"噓","content":"小英雄也只剩下辯論社辯士常用的詭論技倆而已"}]}]}