{"category":"問卦","title":"[問卦] 不戴安全帽騎士買單拆違建全民買單?","author":"monismile","content":"\n不戴安全帽\n\n容易重傷浪費健保\n\n所以強制戴安全帽不然要罰五百台\n\n但違建偷接水電>>>失火燒全家or鄰居?\n\n地基只能蓋五樓偷蓋到十樓>>>小地震就塌?\n\n更可能造成嚴重公安意外\n\n但折違建卻是公家(全民)買單\n\n沒經費就給你一年拆一兩間意思意思\n\n而不是強制違建屋主付費拆屋\n\n\n\n有沒有違建拆除是怎麼立法的八卦\n\n--\n趙敏：人是我殺的，刀是我搶的，怎樣～\n小張：我要殺了妳(#‵′)\n芷若：人是我殺的，刀是我搶的，怎樣～\n小張：哦(下次不可以喔>.^)\n\n　　 《民明書房：明教教主不為人知的另一面》\n\n--\n","pushes":[{"user":"haoto","replies":[{"type":"→","content":"哈哈哈 你被開單了齁"}]},{"user":"joseph0318","replies":[{"type":"推","content":"沒有全民買單吧 事後會追討的"},{"type":"推","content":"法哪有卡在市議會 強制執行法就有法源了"},{"type":"推","content":"行政執行法才對"}]},{"user":"rave760422","replies":[{"type":"→","content":"一直開罰單開到查封房子為止  就會自己拆了"},{"type":"→","content":"每個月最少都開個10萬罰單應該很有效"}]},{"user":"zzxcasd","replies":[{"type":"噓","content":"誰跟你全民買單"}]},{"user":"rainylife","replies":[{"type":"→","content":"會先叫屋主自己拆阿 不拆就政府幫他拆在跟他要錢"}]},{"user":"eddy13","replies":[{"type":"推","content":"法卡在市議會一直無法通過呀，所以不能向屋主要錢。"}]},{"user":"typecommand","replies":[{"type":"→","content":"因為公務員也不想得罪太多人，所以就慢慢拆"}]},{"user":"abyepi","replies":[{"type":"推","content":"因為立法的人都有司機用不到安全帽，但違建會拆到自己家"}]},{"user":"wondtty","replies":[{"type":"推","content":"自己拆比較便宜，公家拆多3倍，讓屋主自己選"}]},{"user":"LinFan","replies":[{"type":"噓","content":"這中文嗎"}]},{"user":"monismile","replies":[{"type":"→","content":"   你新警察嗎"}]},{"user":"reil","replies":[{"type":"推","content":"機車騎士沒地位"}]},{"user":"tissot","replies":[{"type":"推","content":"沒全民買單唷,不過縣市政府還是要先支付該費用,事後追討"},{"type":"→","content":"不過你有聽過罰款可以分期付款嗎?"}]}]}