{"category":"Re:","title":"Re: [問卦] 有沒有佛教不殺生的掛?","author":"gsmzxcvbnm","content":"\n\n  他們是不吃那些有靈性的動物 一堆人拿現代生物學的定義來說嘴古人造的詞句看了就\n覺得很好笑 不然就是在那裡腦補說高麗菜會哭紅蘿蔔會痛有沒有鄉民都那麼感性的八卦\n啊 那OCG也殺了幾億的生命啦\n真是好笑宣傳吃素也不行\n\n--\nSent from my Android\n\n--\n","pushes":[{"user":"blmp1234","replies":[{"type":"→","content":"ocg那個算蛋白質不算生命"},{"type":"→","content":"一個絲襪腳交的概念"}]},{"user":"tutufish","replies":[{"type":"推","content":"OCG是用腳打手槍嗎?"}]},{"user":"cygnuses","replies":[{"type":"→","content":"宣傳吃素對身體比較好沒意見，扯到殺不殺身，那些人比"},{"type":"→","content":"較好笑"},{"type":"→","content":"          殺生"}]}]}