{"category":"Re:","title":"Re: [問卦] 如果 1949 KMT 沒來我國？","author":"DatowZhan","content":"\n\n本肥宅整理了一些資料 後續容我腦補\n\n1945年大日本帝國在第二次世界大戰戰敗投降，並向同盟國簽署《降伏文書》，表明履行\n《波茨坦公告》。1945年10月25日依據盟軍太平洋總司令麥克阿瑟元帥發佈的《一般命令\n第一號》第1條的「軍事命令」規定，中華民國國民政府於台北公會堂（今中山堂）舉行\n受降典禮，陳儀將軍代表蔣介石接受在臺日軍（第十方面軍）的投降，國民政府於此日開\n始軍事接管臺灣。在尚未簽訂和平條約（後來的舊金山和約與中日和約）以正式決定臺灣\n與澎湖的領土轉移之前，國民政府片面宣布恢復對臺灣、澎湖列島之主權，宣告臺灣光復\n。國民政府於10月25日開始實施《台灣接管計劃綱要地方制治》。1946年8月，台灣省行\n政長官公署頒布命令，明訂10月25日為「台灣光復節」為紀念，「臺灣光復」一詞自此（\n1946年）就被各界大量運用。其詞亦有另一說法，表示是緣由自1946年8月由臺灣仕紳籌\n組的台灣光復致敬團。\n\n1946年台灣已受KMT接管\n\n換言之台灣早已不受日軍統治\n\n1949年說回歸日本是不可能的\n\n二二八事件是台灣於1947年2月底發生的大規模民眾反抗政府事件，以及3月至5月間國民\n政府派遣軍隊鎮壓屠殺臺灣人民、捕殺臺籍菁英事件。其中包括民眾與政府的衝突、軍警\n鎮壓平民、當地人對外省人的攻擊，以及臺灣仕紳遭軍警捕殺等等情事。\n\n二二八相關內容維基百科都有，可以去查查\n\n文獻提到相關仕紳多被逮捕罹難\n\n所以要在1949年後由一群仕紳領頭台灣獨立也不太可能\n\n那1949年第二次國共內戰打了那麼久\n\n國民黨被如果沒有逼退台灣\n\n台灣有兩個走向\n\n如果國民黨沒有被逼退台灣\n\n會選擇投降或國共議和\n\n依照老蔣給毛澤東的對立面來看\n\n投降跟議和是不太可能的\n\n就算表面上議和\n\n毛澤東還是會費盡心思的幹掉每一個國民黨員\n\n再者1949年國民黨大勢已去\n\n中國大陸民心多偏向共產黨\n\n中華民國1911年建國以來沒有給老百姓好的生活過\n\n軍閥割據 通貨膨漲 內憂(共)外患(日本)\n\n怪不得孫文會在留下 「革命尚未成功，同志仍須努力」的諫言\n\n既然國共如此不合 國民黨不退守台灣\n\n1949年後最有可能的發展\n\n是國民黨殲滅 共產黨理應接受台灣\n\n接收後台灣依然會民不聊生幾十年\n\n台灣被共產接受 蘇聯當時尚未瓦解\n\n美國就更頭大啦 第三次世界大戰就發生啦\n\n--\nSent from my Android\n\n--\n","pushes":[{"user":"gogobar","replies":[{"type":"推","content":"有一群人會跟你說美國會保護台灣"}]},{"user":"skywingyang","replies":[{"type":"推","content":"所以就會變得跟古巴和越南一樣 一堆殖民時期的建築"},{"type":"→","content":"物"}]},{"user":"ss59418ss","replies":[{"type":"噓","content":"一堆幻想文 當時時空背景 國民黨不來 中共也無能接收台"}]},{"user":"unfinish","replies":[{"type":"推","content":"我想原原po要表達的重點是「不被kmt接管」這事 至於1949"},{"type":"→","content":"年則是他自己搞不清楚狀況造成題意混淆"}]},{"user":"sunnydragon7","replies":[{"type":"→","content":"還是會被中共接收~又不是像外蒙有蘇聯挺~當時美國"},{"type":"→","content":"還沒跟全世界的共產黨翻臉"}]},{"user":"GOPOL","replies":[{"type":"→","content":"KMT沒來台灣就表示被共產黨消滅  這樣的話 根本沒機會"},{"type":"→","content":"在PTT發廢文XD  雖然我討厭KMT 可是不得不承認 沒有他們"},{"type":"→","content":"我們現在就是香港2.0 沒有民主.......沒有選舉"}]},{"user":"fred76963","replies":[{"type":"→","content":"中共沒能力渡海接收是建立在台灣有海空軍的狀況"}]},{"user":"et803","replies":[{"type":"推","content":"有人在幻想了 國共內戰後共匪當時搶灘登陸台灣的能力趨近0"},{"type":"→","content":"別再被沒有kmt台灣會被共匪吞掉的思想洗腦了"}]},{"user":"hhgot","replies":[{"type":"推","content":"台灣在被日本統治前就是清朝中國的領土"},{"type":"→","content":"kmt沒來台，日本就是還給中國，台灣在這之前從沒獨立政權"}]},{"user":"hmnc","replies":[{"type":"推","content":"KMT如1949直接被滅 就算共軍渡海能力差 台灣也幾無自我武力"},{"type":"→","content":"要嘛中共渡海接收台灣(沒有KMT) 不然美國扶植魁儡政權"}]},{"user":"kkchen","replies":[{"type":"推","content":"et803.kmt沒在台灣.為何共匪還需要有搶灘登陸台灣的能力?"}]}]}