{"category":"Re:","title":"Re: [新聞] 「每人只能騙我一次」柯文哲提醒執政團隊","author":"posen2012","content":"\n\n\n屁辣~~ 怒噓！\n\n柯P的確比檯面上的政治人物更讓人感覺清廉和誠懇、最具民心。\n\n但是你要說柯P沒說過謊?\n\n這樣造神下去只會讓他跌的更深。\n\n就當初辯論來說好了\n\n最經典的一句\n\n「我說我是墨綠，是為了證明你的槍傷是真的！」\n\n阿這句話就確確實實是說謊阿...\n\n明明連勝文中彈前好幾年柯P自己就說過了...\n\n凡走過必留下痕跡，歷史都可供所有人去檢驗，\n\n現在估狗都很方便 ，紙是包不住火的。\n\n如果這不是說謊，那什麼才是說謊？\n\n--\n\n只能說 真的站在柯p這邊 就是一起認真的去檢驗他\n\n而不是逢檢驗必反\n\n這種造神團 才是真正的黨工吧... 造神造到神崩壞 然後又毀神 無限循環\n\n好多人都看不懂問題ㄟ...\n\n問題是在於\n\n柯p不是為了救連勝文才變成墨綠的\n\n他很早之前就說過自己是墨綠的\n\n這就是說謊點\n\n","pushes":[{"user":"kasion","replies":[{"type":"→","content":"雨八"}]},{"user":"just8811","replies":[{"type":"推","content":"木"}]},{"user":"higameboy","replies":[{"type":"→","content":"連D：請柯先生退選"}]},{"user":"www5566","replies":[{"type":"→","content":"10年前我說我是蘿莉控 所以10年後我說蘿莉控是假的?"}]},{"user":"skvis","replies":[{"type":"噓","content":"他是拿講過的其中一次出來講... 早就解釋過了"}]},{"user":"nozazero","replies":[{"type":"→","content":"那應該取消黨籍咯"}]},{"user":"davild54849","replies":[{"type":"推","content":"阿扁2.0 貪汙下台叭叭"}]},{"user":"Judicial5566","replies":[{"type":"推","content":"聽你一言 我大夢初醒  看來投柯P是投錯人了"}]},{"user":"aclock","replies":[{"type":"→","content":"說過的東西再說一次不行嗎"}]},{"user":"snow3804","replies":[{"type":"噓","content":"那不是騙只是修正,轉彎而已"},{"type":"→","content":"柯P也不希望替他造神"}]},{"user":"Invec","replies":[{"type":"推","content":"做球給別人殺 還被打到崩潰 可憐喔"}]},{"user":"viceversa56","replies":[{"type":"→","content":"人總會修正吧, 你以前投KMT,現在就會投KMT?"},{"type":"→","content":"他那樣說也沒錯, 當初大家都不信是真的, 他那樣說"},{"type":"→","content":"直接讓綠色閉嘴"},{"type":"→","content":"不像有些人就算知道是真的,也沒出來說話"},{"type":"→","content":"他以前有說過沒錯啊,但中彈有多少人對得起良知想說?"},{"type":"→","content":"中彈之前講的是他的立場, 每個人立場本來就不同"},{"type":"→","content":"到現在還是有人在藍綠惡鬥的思維,腦袋要進步一點"},{"type":"→","content":"他之前講的也沒錯, 那是柯P以前的立場,不代表現在"},{"type":"→","content":"沒人說不是 albert 你就不要跳針了..."},{"type":"→","content":"他沒說謊,有時光機回到以前問他這個問題 他一定是綠"},{"type":"→","content":"但現在再問他這個問題, 他變成白色, 這是進步"},{"type":"→","content":"我以前挺KMT, 現在挺白色,你說我對你以前說謊"},{"type":"→","content":"這不就是邏輯的謬誤"},{"type":"→","content":"人的思維會一直變, 包含喜歡的偶像藝人也是..."},{"type":"→","content":"以前討厭5566, 中間時間喜歡5566 後來又討厭5566"},{"type":"→","content":"這也可以套用九把刀, 阿基師"},{"type":"→","content":"老實說有一種人最爛,就是含淚支持 (思維永不會進步)"},{"type":"噓","content":"不要用 \"現在\"的你質疑\"過去\"的我  這是時態的問題"},{"type":"→","content":"阿基師滑進薇閤, 你會用以前數據來說明他人氣很高?"},{"type":"→","content":"連勝文就是用過去的柯P 質疑現在的柯P還是深綠"},{"type":"→","content":"你說柯P有可能會在變成黑色或是其他顏色,我只能說有"},{"type":"→","content":"可能,這是未來時態的問題, 但不代表說謊"},{"type":"→","content":"用亞斯患者攻擊他人..我只能說有些人水平真是..."},{"type":"→","content":"你要嘛講贏人,不要在那邏輯不通開始類比誰"},{"type":"→","content":"這是個講理的時代...所以東西都可以討論 但不要跳針"}]},{"user":"pilifonbao","replies":[{"type":"→","content":"..."}]},{"user":"heavensun","replies":[{"type":"推","content":"柯的確有語病  如果科說謊 人民要罷免他嗎?"}]},{"user":"SuperUp","replies":[{"type":"噓","content":":"},{"type":"噓","content":"好可憐喔 打到没有東西可以打了 開始鑽牛角尖"},{"type":"噓","content":"好啦 別再鑽啦 快去把邏輯課程修一修 八掛版水準該提升囉"},{"type":"→","content":"這種話術現在已經只能騙騙深藍了 人民都進步了"},{"type":"→","content":"柯老早就說過自己綠的了 跟連這件事跟本不牴觸"},{"type":"→","content":"是有人在說謊? 還是有人邏輯太差?"},{"type":"→","content":"只會在哪邊喊造神柯P 先去管管馬英九吧 國家都快爛掉了"}]},{"user":"albert","replies":[{"type":"→","content":"原Po的意思是:在連勝文中彈之前,柯P就有說過自己是墨綠了"},{"type":"→","content":"所以中彈之前講的一定不是為了證明槍傷而講的"},{"type":"→","content":"所以「我說我是墨綠，是為了證明你的槍傷是真的！」是假的"},{"type":"→","content":"簡單的說就譬如是人家質疑你 2008 年你說你是墨綠"},{"type":"→","content":"結果你說「我說我是墨綠，是為了證明你的槍傷是真的！」"},{"type":"→","content":"可是我槍傷是 2010 年的事啊?!!"},{"type":"→","content":"柯P那句話在連槍傷時是對的沒錯，但對那之前說的是錯的"},{"type":"→","content":"人家是問你很久前就說你自己是墨綠,不是只問槍傷那次講的"},{"type":"→","content":"槍傷那次是為了證明槍傷沒錯，但其他幾次就都不是了"}]},{"user":"nepenthes7","replies":[{"type":"推","content":"然後呢 跟勝文中槍這件事何干"},{"type":"推","content":"哪是假的 邏輯有問題逆"},{"type":"→","content":"跟這有何關係 柯就是用墨綠身份擔保了阿"},{"type":"→","content":"他這樣講哪有問題"},{"type":"推","content":"所以他可以這樣講阿 有問題嗎"},{"type":"→","content":"誰知道你神豬是要問哪時候 畜牲頭腦不好阿"},{"type":"推","content":"因為豬想打藍綠 問題還問的讓人家能反打"},{"type":"→","content":"是神豬智商問題不是柯的問題阿"},{"type":"→","content":"就算墨綠不能同時希望藍綠合解嗎"},{"type":"→","content":"只能說是神豬一直笨到想打藍綠基本盤這塊"}]},{"user":"arod18818","replies":[{"type":"噓","content":"會做事就好 你管這麼多"},{"type":"噓","content":"一句話可以讓你崩潰這麼久 別草莓了"},{"type":"噓","content":"墨綠墨藍干你屁事  台灣已經被搞爛6年了才重要"},{"type":"→","content":"輸不起的 一輩子就陷在藍綠吧"},{"type":"→","content":"別當台灣發展的拌腳石"}]},{"user":"potionx","replies":[{"type":"→","content":"這個一定是文組的想法"}]},{"user":"polor","replies":[{"type":"噓","content":"那連d槍傷你就不要相信吧"}]},{"user":"rockonpizza3","replies":[{"type":"→","content":"以前3歲只會爬,現在能走路~前後不一喔~"}]},{"user":"lymyuming","replies":[{"type":"噓","content":"真可憐~~~~是要崩到什麼時候啊"}]},{"user":"Raogo","replies":[{"type":"→","content":"我不懂你想表達甚麼= ="},{"type":"→","content":"D中槍前幾年講過的話，跟中槍之後的墨綠說有甚麼關係?"},{"type":"→","content":"那不就對了嗎? = ="},{"type":"→","content":"albert自己都解釋清楚了阿，怎麼還覺得是假的"},{"type":"→","content":"問題在於這不是造神，只是在鑽牛角尖"}]},{"user":"finzaghi","replies":[{"type":"噓","content":":"}]},{"user":"cancboy","replies":[{"type":"噓","content":"那句話那裡說謊? 以前講過同一句，後來也講同一句 說謊?"},{"type":"噓","content":"你嘛幫幫忙 你才不懂 很早說的跟救連勝文說的有不一樣嗎"}]},{"user":"GORDON2037","replies":[{"type":"噓","content":"...悲憤了?"}]},{"user":"a6300072","replies":[{"type":"推","content":"689的人會檢討連D團隊一天到晚在抹黑嗎？真是笑話"},{"type":"推","content":"不過我們正藍軍本來就高人一等，不用檢討也是很合理的"}]},{"user":"fishbliss","replies":[{"type":"噓","content":"唉"}]},{"user":"chosenone","replies":[{"type":"推","content":"八卦的水準真的很差 摸摸自己LP 有人敢講自己沒說過謊?"},{"type":"→","content":"挺柯是一回事 柯拉的屎都能說很香 那不是白痴就是反串"},{"type":"推","content":"有些柯P支持者越來越像當年的馬迷了"}]},{"user":"izna","replies":[{"type":"→","content":"雖然是冷話題了 可是部分的亞斯患者會有這種情形"},{"type":"→","content":"完全不承認自己曾經做過的事、說過的話，且會認為聲稱看過、"},{"type":"→","content":"聽過自己說過那些話的人很奇怪 自己明明就沒有說過"},{"type":"→","content":"我不知道動機 但認識的亞斯患者週期性的常會這樣"},{"type":"→","content":"例如今天說我最喜歡吃蘋果，明天就當眾說：我明明說我最討厭"},{"type":"→","content":"蘋果的 你們怎麼會全部都記錯呢？"}]},{"user":"mvp04","replies":[{"type":"噓","content":"邏輯好一點再來po文"}]},{"user":"skyringcha","replies":[{"type":"噓","content":"...............我建議你從幼稚園開始重唸起"}]}]}