{"category":"Re:","title":"Re: [問卦] EMAIL要怎樣才能白回來?","author":"BleedWang","content":"\n\n\n沒必要白回來\n\n當初只是利用這裡的無腦肥宅 讓自己成名\n\n現在目的已經達到 釣到不錯的金龜婿\n\n你以為她還會care這邊的肥宅嗎\n\n每篇都把她噓到XX 她也懶得理你\n\n--\n","pushes":[{"user":"Lailungsheng","replies":[{"type":"推","content":"再見了，前妻"}]},{"user":"ok5566","replies":[{"type":"推","content":"$$$$$$$$$$$$$$$$$ > 肥宅的虛幻吹捧"}]},{"user":"hipab","replies":[{"type":"推","content":"還需要說嗎 當然是           感謝祭"}]},{"user":"TSbb","replies":[{"type":"推","content":"推一下自介文，真的很氣 XD"}]},{"user":"Halu5566","replies":[{"type":"推","content":"還永遠有一批不離不棄的粉絲 不管她怎麼講都挺她"}]},{"user":"koxinga","replies":[{"type":"推","content":"在當正義記者"}]},{"user":"crea0520","replies":[{"type":"推","content":"他真的是裝無辜還是真無辜啊？都分不清他真實想法了…"}]},{"user":"clamperni","replies":[{"type":"推","content":"真的 還開一隻5566的帳號完全就是為了討好鄉民來著"}]},{"user":"ymx3xc","replies":[{"type":"→","content":"她之前當主播時的付出我是正面肯定~但近期就讓人看不懂..."}]},{"user":"lea109","replies":[{"type":"噓","content":"她那一句“鄉民容易被操弄” 就已經在我心中白回來了!"},{"type":"→","content":"這麼中肯的一句話 怎麼能不白？誰像她敢講 管他男友是誰"}]},{"user":"eddie04","replies":[{"type":"推","content":"你看他現在還會不會回來理你就知道了"}]},{"user":"sy4826951","replies":[{"type":"推","content":"中肯啊"}]}]}